LICENSE
MANIFEST.in
README.md
setup.py
./requirements/requirements.txt
neural_ilt.egg-info/PKG-INFO
neural_ilt.egg-info/SOURCES.txt
neural_ilt.egg-info/dependency_links.txt
neural_ilt.egg-info/requires.txt
neural_ilt.egg-info/top_level.txt
neural_ilt_package/VERSION
neural_ilt_package/__init__.py
neural_ilt_package/eval.py
neural_ilt_package/ilt_loss_layer.py
neural_ilt_package/neural_ilt.py
neural_ilt_package/neural_ilt_backbone.py
neural_ilt_package/pretrain_model.py
neural_ilt_package/dataloader/__init__.py
neural_ilt_package/dataloader/refine_data_loader.py
neural_ilt_package/dataloader/train_data_loader.py
neural_ilt_package/dataset/ibm_opc_test_full_list.txt
neural_ilt_package/dataset/ibm_opc_test/t10_0_mask.png
neural_ilt_package/dataset/ibm_opc_test/t11_0_mask.png
neural_ilt_package/dataset/ibm_opc_test/t12_0_mask.png
neural_ilt_package/dataset/ibm_opc_test/t13_0_mask.png
neural_ilt_package/dataset/ibm_opc_test/t14_0_mask.png
neural_ilt_package/dataset/ibm_opc_test/t15_0_mask.png
neural_ilt_package/dataset/ibm_opc_test/t16_0_mask.png
neural_ilt_package/dataset/ibm_opc_test/t17_0_mask.png
neural_ilt_package/dataset/ibm_opc_test/t18_0_mask.png
neural_ilt_package/dataset/ibm_opc_test/t19_0_mask.png
neural_ilt_package/dataset/ibm_opc_test/t1_0_mask.png
neural_ilt_package/dataset/ibm_opc_test/t20_0_mask.png
neural_ilt_package/dataset/ibm_opc_test/t2_0_mask.png
neural_ilt_package/dataset/ibm_opc_test/t3_0_mask.png
neural_ilt_package/dataset/ibm_opc_test/t4_0_mask.png
neural_ilt_package/dataset/ibm_opc_test/t5_0_mask.png
neural_ilt_package/dataset/ibm_opc_test/t6_0_mask.png
neural_ilt_package/dataset/ibm_opc_test/t7_0_mask.png
neural_ilt_package/dataset/ibm_opc_test/t8_0_mask.png
neural_ilt_package/dataset/ibm_opc_test/t9_0_mask.png
neural_ilt_package/lithosim/__init__.py
neural_ilt_package/lithosim/lithosim_cuda.py
neural_ilt_package/lithosim/run_litho_sim_batch.py
neural_ilt_package/lithosim/lithosim_kernels/torch_tensor/kernel_ct_defocus_tensor.pt
neural_ilt_package/lithosim/lithosim_kernels/torch_tensor/kernel_ct_focus_tensor.pt
neural_ilt_package/lithosim/lithosim_kernels/torch_tensor/kernel_defocus_tensor.pt
