Metadata-Version: 2.1
Name: neural-ilt
Version: 1.0.0
Summary: Litography mask generation with neural networks
Home-page: https://github.com/cuhk-eda/neural-ilt
Author: 
Author-email: 
License: CU-SD LICENSE
Platform: UNKNOWN
Classifier: Intended Audience :: Developers
Classifier: Intended Audience :: Science/Research
Classifier: Programming Language :: Python
Classifier: Programming Language :: Python :: 3
Classifier: Programming Language :: Python :: Implementation :: PyPy
Classifier: Topic :: Software Development :: Libraries
Classifier: Topic :: Software Development :: Libraries :: Python Modules
Requires-Python: >=3.6.0
License-File: LICENSE
